odoo8_addon_l10n_nl_partner_salutation-8.0.1.0.0-py2.7-nspkg.pth
odoo8_addon_l10n_nl_partner_salutation-8.0.1.0.0.dist-info/top_level.txt
odoo8_addon_l10n_nl_partner_salutation-8.0.1.0.0.dist-info/WHEEL
odoo8_addon_l10n_nl_partner_salutation-8.0.1.0.0.dist-info/RECORD
odoo8_addon_l10n_nl_partner_salutation-8.0.1.0.0.dist-info/metadata.json
odoo8_addon_l10n_nl_partner_salutation-8.0.1.0.0.dist-info/DESCRIPTION.rst
odoo8_addon_l10n_nl_partner_salutation-8.0.1.0.0.dist-info/METADATA
odoo8_addon_l10n_nl_partner_salutation-8.0.1.0.0.dist-info/namespace_packages.txt
odoo_addons/l10n_nl_partner_salutation/__openerp__.py
odoo_addons/l10n_nl_partner_salutation/__init__.py
odoo_addons/l10n_nl_partner_salutation/README.rst
odoo_addons/l10n_nl_partner_salutation/view/res_partner.xml
odoo_addons/l10n_nl_partner_salutation/view/res_partner_title.xml
odoo_addons/l10n_nl_partner_salutation/i18n/l10n_nl_partner_salutation.pot
odoo_addons/l10n_nl_partner_salutation/i18n/nl.po
odoo_addons/l10n_nl_partner_salutation/model/res_partner.py
odoo_addons/l10n_nl_partner_salutation/model/__init__.py
odoo_addons/l10n_nl_partner_salutation/model/res_partner_title.py
odoo_addons/l10n_nl_partner_salutation/data/res_partner_title.xml
