Metadata-Version: 2.0
Name: odoo8-addon-l10n-nl-partner-salutation
Version: 8.0.1.0.0
Summary: Full salutation for partners, Dutch style
Home-page: UNKNOWN
Author: UNKNOWN
Author-email: UNKNOWN
License: UNKNOWN
Platform: UNKNOWN
Requires-Dist: odoo (<9.0a,>=8.0a)
Requires-Dist: odoo8-addon-l10n-nl-partner-name
Classifier: Programming Language :: Python :: 2.7
Classifier: Framework :: Odoo
